mtm_asset_packer.py
mtm_asset_packer-1.0.3.dist-info/METADATA
mtm_asset_packer-1.0.3.dist-info/WHEEL
mtm_asset_packer-1.0.3.dist-info/entry_points.txt
mtm_asset_packer-1.0.3.dist-info/RECORD
