Metadata-Version: 2.4
Name: mtm-asset-packer
Version: 1.0.3
Summary: An improved asset packer script to make the process of creating and packing asset packs for the Momentum firmware easier.
Author-email: notnotnescap <97590612+nescapp@users.noreply.github.com>
Requires-Python: >=3.11
Requires-Dist: heatshrink2>=0.13.0
Requires-Dist: pillow>=11.2.1
